imagecodecs/__init__.py
imagecodecs/__init__.pyi
imagecodecs/__main__.py
imagecodecs/_aec.cp314t-win32.pyd
imagecodecs/_apng.cp314t-win32.pyd
imagecodecs/_avif.cp314t-win32.pyd
imagecodecs/_bcn.cp314t-win32.pyd
imagecodecs/_bitshuffle.cp314t-win32.pyd
imagecodecs/_blosc.cp314t-win32.pyd
imagecodecs/_blosc2.cp314t-win32.pyd
imagecodecs/_bmp.cp314t-win32.pyd
imagecodecs/_brotli.cp314t-win32.pyd
imagecodecs/_bz2.cp314t-win32.pyd
imagecodecs/_cms.cp314t-win32.pyd
imagecodecs/_deflate.cp314t-win32.pyd
imagecodecs/_gif.cp314t-win32.pyd
imagecodecs/_h5checksum.cp314t-win32.pyd
imagecodecs/_htj2k.cp314t-win32.pyd
imagecodecs/_imagecodecs.py
imagecodecs/_imcd.cp314t-win32.pyd
imagecodecs/_jpeg2k.cp314t-win32.pyd
imagecodecs/_jpeg8.cp314t-win32.pyd
imagecodecs/_jpegls.cp314t-win32.pyd
imagecodecs/_jpegsof3.cp314t-win32.pyd
imagecodecs/_jpegxl.cp314t-win32.pyd
imagecodecs/_jpegxr.cp314t-win32.pyd
imagecodecs/_jpegxs.cp314t-win32.pyd
imagecodecs/_lerc.cp314t-win32.pyd
imagecodecs/_ljpeg.cp314t-win32.pyd
imagecodecs/_lz4.cp314t-win32.pyd
imagecodecs/_lz4f.cp314t-win32.pyd
imagecodecs/_lzf.cp314t-win32.pyd
imagecodecs/_lzfse.cp314t-win32.pyd
imagecodecs/_lzham.cp314t-win32.pyd
imagecodecs/_lzma.cp314t-win32.pyd
imagecodecs/_lzo.cp314t-win32.pyd
imagecodecs/_meshopt.cp314t-win32.pyd
imagecodecs/_mozjpeg.cp314t-win32.pyd
imagecodecs/_pglz.cp314t-win32.pyd
imagecodecs/_png.cp314t-win32.pyd
imagecodecs/_qoi.cp314t-win32.pyd
imagecodecs/_quantize.cp314t-win32.pyd
imagecodecs/_rcomp.cp314t-win32.pyd
imagecodecs/_rgbe.cp314t-win32.pyd
imagecodecs/_shared.cp314t-win32.pyd
imagecodecs/_shared_cython.cp314t-win32.pyd
imagecodecs/_snappy.cp314t-win32.pyd
imagecodecs/_spng.cp314t-win32.pyd
imagecodecs/_sz3.cp314t-win32.pyd
imagecodecs/_szip.cp314t-win32.pyd
imagecodecs/_tiff.cp314t-win32.pyd
imagecodecs/_ultrahdr.cp314t-win32.pyd
imagecodecs/_webp.cp314t-win32.pyd
imagecodecs/_zfp.cp314t-win32.pyd
imagecodecs/_zlib.cp314t-win32.pyd
imagecodecs/_zlibng.cp314t-win32.pyd
imagecodecs-2026.1.1.dist-info/licenses/LICENSE
imagecodecs-2026.1.1.dist-info/METADATA
imagecodecs-2026.1.1.dist-info/WHEEL
imagecodecs-2026.1.1.dist-info/entry_points.txt
imagecodecs-2026.1.1.dist-info/top_level.txt
imagecodecs-2026.1.1.dist-info/RECORD
