Metadata-Version: 2.4
Name: imagecodecs
Version: 2026.1.1
Summary: Image transformation, compression, and decompression codecs
Home-page: https://www.cgohlke.com
Author: Christoph Gohlke
Author-email: cgohlke@cgohlke.com
License: BSD-3-Clause
Project-URL: Bug Tracker, https://github.com/cgohlke/imagecodecs/issues
Project-URL: Source Code, https://github.com/cgohlke/imagecodecs
Platform: any
Classifier: Development Status :: 4 - Beta
Classifier: Intended Audience :: Science/Research
Classifier: Intended Audience :: Developers
Classifier: Operating System :: OS Independent
Classifier: Programming Language :: C
Classifier: Programming Language :: Cython
Classifier: Programming Language :: Python :: 3 :: Only
Classifier: Programming Language :: Python :: 3.11
Classifier: Programming Language :: Python :: 3.12
Classifier: Programming Language :: Python :: 3.13
Classifier: Programming Language :: Python :: 3.14
Classifier: Programming Language :: Python :: Implementation :: CPython
Requires-Python: >=3.11
License-File: LICENSE
Requires-Dist: numpy
Provides-Extra: all
Requires-Dist: matplotlib; extra == "all"
Requires-Dist: tifffile; extra == "all"
Requires-Dist: numcodecs; extra == "all"
Provides-Extra: test
Requires-Dist: pytest; extra == "test"
Requires-Dist: pytest-run-parallel; extra == "test"
Requires-Dist: tifffile; extra == "test"
Requires-Dist: czifile; extra == "test"
Requires-Dist: liffile; extra == "test"
Requires-Dist: backports.zstd; extra == "test"
Requires-Dist: blosc; extra == "test"
Requires-Dist: blosc2; extra == "test"
Requires-Dist: brotli; extra == "test"
Requires-Dist: lz4; extra == "test"
Requires-Dist: pyliblzfse; extra == "test"
Requires-Dist: python-lzf; extra == "test"
Requires-Dist: python-snappy; extra == "test"
Requires-Dist: bitshuffle; extra == "test"
Requires-Dist: zopflipy; extra == "test"
Requires-Dist: zarr; extra == "test"
Requires-Dist: numcodecs; extra == "test"
Requires-Dist: kerchunk; extra == "test"
Dynamic: author
Dynamic: author-email
Dynamic: classifier
Dynamic: description
Dynamic: description-content-type
Dynamic: home-page
Dynamic: license
Dynamic: license-file
Dynamic: platform
Dynamic: project-url
Dynamic: provides-extra
Dynamic: requires-dist
Dynamic: requires-python
Dynamic: summary
